theme_eliiza/__init__.py
theme_eliiza/plotnine.py
theme_eliiza/data/Poppins-Regular.ttf
theme_eliiza/data/Roboto-Regular.ttf
theme_eliiza/data/eliiza.mplstyle
theme_eliiza-0.1.dist-info/LICENSE
theme_eliiza-0.1.dist-info/METADATA
theme_eliiza-0.1.dist-info/WHEEL
theme_eliiza-0.1.dist-info/top_level.txt
theme_eliiza-0.1.dist-info/RECORD
