Metadata-Version: 2.1
Name: theme-eliiza
Version: 0.1
Summary: ggplot theme for eliiza graphics
Home-page: http://github.com/eliiza/theme-eliiza
Author: Patrick Robotham
Author-email: patrick.robotham@eliiza.com.au
License: MIT
Platform: UNKNOWN
Requires-Dist: plotnine
Requires-Dist: matplotlib
